hkopenai/hk_finance_mcp_server/__init__.py
hkopenai/hk_finance_mcp_server/__main__.py
hkopenai/hk_finance_mcp_server/server.py
mseep_hkopenai_hk_finance_mcp_server-0.1.8.dist-info/licenses/LICENSE
mseep_hkopenai_hk_finance_mcp_server-0.1.8.dist-info/METADATA
mseep_hkopenai_hk_finance_mcp_server-0.1.8.dist-info/WHEEL
mseep_hkopenai_hk_finance_mcp_server-0.1.8.dist-info/entry_points.txt
mseep_hkopenai_hk_finance_mcp_server-0.1.8.dist-info/top_level.txt
mseep_hkopenai_hk_finance_mcp_server-0.1.8.dist-info/RECORD
